bong16/__init__.py
bong16/bong16.py
bong16-0.1.0.dist-info/licenses/LICENSE
bong16-0.1.0.dist-info/METADATA
bong16-0.1.0.dist-info/WHEEL
bong16-0.1.0.dist-info/top_level.txt
bong16-0.1.0.dist-info/RECORD
